f5xc_py_substrate/__init__.py
f5xc_py_substrate/_http.py
f5xc_py_substrate/client.py
f5xc_py_substrate/exceptions.py
f5xc_py_substrate/models.py
f5xc_py_substrate/resources/__init__.py
f5xc_py_substrate/resources/addon_service/__init__.py
f5xc_py_substrate/resources/addon_service/models.py
f5xc_py_substrate/resources/addon_service/resource.py
f5xc_py_substrate/resources/addon_subscription/__init__.py
f5xc_py_substrate/resources/addon_subscription/models.py
f5xc_py_substrate/resources/addon_subscription/resource.py
f5xc_py_substrate/resources/address_allocator/__init__.py
f5xc_py_substrate/resources/address_allocator/models.py
f5xc_py_substrate/resources/address_allocator/resource.py
f5xc_py_substrate/resources/advertise_policy/__init__.py
f5xc_py_substrate/resources/advertise_policy/models.py
f5xc_py_substrate/resources/advertise_policy/resource.py
f5xc_py_substrate/resources/ai_assistant/__init__.py
f5xc_py_substrate/resources/ai_assistant/models.py
f5xc_py_substrate/resources/ai_assistant/resource.py
f5xc_py_substrate/resources/alert/__init__.py
f5xc_py_substrate/resources/alert/models.py
f5xc_py_substrate/resources/alert/resource.py
f5xc_py_substrate/resources/alert_gen_policy/__init__.py
f5xc_py_substrate/resources/alert_gen_policy/models.py
f5xc_py_substrate/resources/alert_gen_policy/resource.py
f5xc_py_substrate/resources/alert_policy/__init__.py
f5xc_py_substrate/resources/alert_policy/models.py
f5xc_py_substrate/resources/alert_policy/resource.py
f5xc_py_substrate/resources/alert_receiver/__init__.py
f5xc_py_substrate/resources/alert_receiver/models.py
f5xc_py_substrate/resources/alert_receiver/resource.py
f5xc_py_substrate/resources/alert_template/__init__.py
f5xc_py_substrate/resources/alert_template/models.py
f5xc_py_substrate/resources/alert_template/resource.py
f5xc_py_substrate/resources/allowed_domain/__init__.py
f5xc_py_substrate/resources/allowed_domain/models.py
f5xc_py_substrate/resources/allowed_domain/resource.py
f5xc_py_substrate-0.1.0.dist-info/METADATA
f5xc_py_substrate-0.1.0.dist-info/WHEEL
f5xc_py_substrate-0.1.0.dist-info/entry_points.txt
f5xc_py_substrate-0.1.0.dist-info/licenses/LICENSE
f5xc_py_substrate-0.1.0.dist-info/RECORD
