Metadata-Version: 2.4
Name: f5xc-py-substrate
Version: 0.1.0
Summary: Python SDK for F5 Distributed Cloud APIs
Author: Kevin
License: Unlicense
License-File: LICENSE
Requires-Python: >=3.9
Requires-Dist: httpx>=0.25.0
Requires-Dist: pydantic>=2.0.0
Provides-Extra: all
Requires-Dist: jinja2>=3.0.0; extra == 'all'
Requires-Dist: mypy>=1.0.0; extra == 'all'
Requires-Dist: pytest-cov>=4.0.0; extra == 'all'
Requires-Dist: pytest-dependency>=0.5.0; extra == 'all'
Requires-Dist: pytest-httpx>=0.21.0; extra == 'all'
Requires-Dist: pytest-json-report>=1.5.0; extra == 'all'
Requires-Dist: pytest-order>=1.0.0; extra == 'all'
Requires-Dist: pytest>=7.0.0; extra == 'all'
Requires-Dist: python-dotenv>=1.0.0; extra == 'all'
Requires-Dist: pyyaml>=6.0; extra == 'all'
Requires-Dist: ruff>=0.1.0; extra == 'all'
Provides-Extra: dev
Requires-Dist: mypy>=1.0.0; extra == 'dev'
Requires-Dist: pytest-cov>=4.0.0; extra == 'dev'
Requires-Dist: pytest-dependency>=0.5.0; extra == 'dev'
Requires-Dist: pytest-httpx>=0.21.0; extra == 'dev'
Requires-Dist: pytest-json-report>=1.5.0; extra == 'dev'
Requires-Dist: pytest-order>=1.0.0; extra == 'dev'
Requires-Dist: pytest>=7.0.0; extra == 'dev'
Requires-Dist: python-dotenv>=1.0.0; extra == 'dev'
Requires-Dist: ruff>=0.1.0; extra == 'dev'
Provides-Extra: generator
Requires-Dist: jinja2>=3.0.0; extra == 'generator'
Provides-Extra: yaml
Requires-Dist: pyyaml>=6.0; extra == 'yaml'
